progen_transformer/__init__.py
progen_transformer/checkpoint.py
progen_transformer/data.py
progen_transformer/progen.py
progen_transformer/utils.py
progen_transformer-0.0.36.dist-info/LICENSE
progen_transformer-0.0.36.dist-info/METADATA
progen_transformer-0.0.36.dist-info/WHEEL
progen_transformer-0.0.36.dist-info/top_level.txt
progen_transformer-0.0.36.dist-info/RECORD
